codedecide/__init__.py
codedecide/df.py
codedecide/indicators.py
codedecide/plots.py
codedecide-0.1.4.dist-info/LICENSE
codedecide-0.1.4.dist-info/METADATA
codedecide-0.1.4.dist-info/WHEEL
codedecide-0.1.4.dist-info/RECORD
